{
  "water_requests": [
  {
    "id": 1,
    "resident_id": 101,
    "provider_id": 201,
    "requested_liters": 30,
    "status": "pending",
    "delivered_at": null
  },
  {
    "id": 2,
    "resident_id": 102,
    "provider_id": 202,
    "requested_liters": 45,
    "status": "delivered",
    "delivered_at": "2025-05-10T09:15:00"
  },
  {
    "id": 3,
    "resident_id": 103,
    "provider_id": 203,
    "requested_liters": 60,
    "status": "cancelled",
    "delivered_at": null
  },
  {
    "id": 4,
    "resident_id": 104,
    "provider_id": 204,
    "requested_liters": 50,
    "status": "pending",
    "delivered_at": null
  },
  {
    "id": 5,
    "resident_id": 105,
    "provider_id": 201,
    "requested_liters": 25,
    "status": "delivered",
    "delivered_at": "2025-05-09T17:45:00"
  },
  {
    "id": 6,
    "resident_id": 106,
    "provider_id": 202,
    "requested_liters": 40,
    "status": "delivered",
    "delivered_at": "2025-05-10T12:00:00"
  },
  {
    "id": 7,
    "resident_id": 107,
    "provider_id": 203,
    "requested_liters": 55,
    "status": "pending",
    "delivered_at": null
  },
  {
    "id": 8,
    "resident_id": 108,
    "provider_id": 204,
    "requested_liters": 35,
    "status": "delivered",
    "delivered_at": "2025-05-11T08:30:00"
  },
  {
    "id": 9,
    "resident_id": 109,
    "provider_id": 201,
    "requested_liters": 20,
    "status": "cancelled",
    "delivered_at": null
  },
  {
    "id": 10,
    "resident_id": 110,
    "provider_id": 202,
    "requested_liters": 45,
    "status": "delivered",
    "delivered_at": "2025-05-11T13:00:00"
  },
  {
    "id": 11,
    "resident_id": 111,
    "provider_id": 203,
    "requested_liters": 50,
    "status": "pending",
    "delivered_at": null
  },
  {
    "id": 12,
    "resident_id": 112,
    "provider_id": 204,
    "requested_liters": 60,
    "status": "delivered",
    "delivered_at": "2025-05-12T10:15:00"
  }
]
}
